[{"domain":".paypal.com","expirationDate":1765806992.475542,"hostOnly":false,"httpOnly":false,"name":"enforce_policy","path":"/","sameSite":"no_restriction","secure":true,"session":false,"storeId":"0","value":"ccpa"},{"domain":".paypal.com","expirationDate":1765806989.426664,"hostOnly":false,"httpOnly":false,"name":"TLTDID","path":"/","sameSite":"lax","secure":false,"session":false,"storeId":"0","value":"58246327518837335994604367730665"},{"domain":".paypal.com","expirationDate":1767531171.524037,"hostOnly":false,"httpOnly":true,"name":"cookie_check","path":"/","sameSite":"no_restriction","secure":true,"session":false,"storeId":"0","value":"yes"},{"domain":".paypal.com","expirationDate":1767531211.561524,"hostOnly":false,"httpOnly":true,"name":"d_id","path":"/","sameSite":"no_restriction","secure":true,"session":false,"storeId":"0","value":"814fdf25cbba478c911b5ab1bd56b7491732971171330"},{"domain":".paypal.com","expirationDate":1764507186.242516,"hostOnly":false,"httpOnly":true,"name":"_iidt","path":"/","sameSite":"no_restriction","secure":true,"session":false,"storeId":"0","value":"4DwSbnPmtGD8bLLnnh4JzO2qTV9ls51gwOK9ornMm9UF0hxqNa7Eq0KwB5+iqZSSxW1jFm1HmmY1b48W6Mk6atU8bk9OeTz2IzuK9rk="},{"domain":".paypal.com","expirationDate":1768372406.813413,"hostOnly":false,"httpOnly":true,"name":"login_email","path":"/","sameSite":"no_restriction","secure":true,"session":false,"storeId":"0","value":"mattcw9090%40gmail.com"},{"domain":".paypal.com","expirationDate":1767531211.561457,"hostOnly":false,"httpOnly":true,"name":"TfXMWj95u2_Zf1Kmv_GCUOjlGG8","path":"/","sameSite":"no_restriction","secure":true,"session":false,"storeId":"0","value":"LAPWusVPZaVzXWfmrdQRPaY2-UpGvKuasN9xnjOX3OKLCUEkf2vVPSiNvDTFRWE6y5i9kr3ax-HsMFVJRzDoxdTpqJyltxbh4gFuFJQDO8aSYctKzESXyA2GBvErlaBSQ6BccYrQvGgMebUOsHOopjmb6U96HLstXLuaIK70ZYUaeyMyEFRL6iYkcxkZqMR5IwI3Z0"},{"domain":".paypal.com","expirationDate":1768372340.162692,"hostOnly":false,"httpOnly":true,"name":"ui_experience","path":"/","sameSite":"no_restriction","secure":true,"session":false,"storeId":"0","value":"did_set%3Dtrue%26login_type%3DPHONE_PASSWORD"},{"domain":".paypal.com","expirationDate":1765348620.841563,"hostOnly":false,"httpOnly":false,"name":"cookie_prefs","path":"/","sameSite":"no_restriction","secure":true,"session":false,"storeId":"0","value":"T%3D1%2CP%3D1%2CF%3D1%2Ctype%3Dexplicit_banner"},{"domain":".paypal.com","expirationDate":1742046989,"hostOnly":false,"httpOnly":false,"name":"_gcl_au","path":"/","sameSite":"unspecified","secure":false,"session":false,"storeId":"0","value":"1.1.1048140676.1733812621"},{"domain":".paypal.com","expirationDate":1768830986.949262,"hostOnly":false,"httpOnly":true,"name":"rmuc","path":"/","sameSite":"no_restriction","secure":true,"session":false,"storeId":"0","value":"kej5gwXTsWnrZtsdnYSaHp0gAKj1BmmNWVjtdZQvBs6kqwMyI0W9-fkrJUZeExJDgNlUo1dTIO5m0Ko89Ql_ENOqOMqz1Yoqm8M7hS1QzWfFVkbvJel8zG1na96DSrFV8aiw0MqxSTO0qNIPikQkn_UWqxil1hpo5DcD48sb8CcHKmDoTQsdg92uIZhLnxlXOKKmFW"},{"domain":".paypal.com","expirationDate":1734302548.475667,"hostOnly":false,"httpOnly":true,"name":"LANG","path":"/","sameSite":"no_restriction","secure":true,"session":false,"storeId":"0","value":"en_AU%3BAU"},{"domain":".paypal.com","expirationDate":1734357389,"hostOnly":false,"httpOnly":false,"name":"_gid","path":"/","sameSite":"unspecified","secure":false,"session":false,"storeId":"0","value":"GA1.2.1509191470.1734263205"},{"domain":"www.paypal.com","expirationDate":1768830977.258906,"hostOnly":true,"httpOnly":true,"name":"pi_opt_in925803","path":"/","sameSite":"no_restriction","secure":true,"session":false,"storeId":"0","value":"true"},{"domain":"www.paypal.com","expirationDate":1768830977.25896,"hostOnly":true,"httpOnly":true,"name":"visitor_id925803-hash","path":"/","sameSite":"no_restriction","secure":true,"session":false,"storeId":"0","value":"2e450d93628823a99e63abab400ec60f86722c4740f988b528c6aca1d688e95bbe29111942322f86a69c8f75fb578a6d524932c4"},{"domain":"www.paypal.com","expirationDate":1768830977.259151,"hostOnly":true,"httpOnly":true,"name":"visitor_id925803","path":"/","sameSite":"no_restriction","secure":true,"session":false,"storeId":"0","value":"3540477283"},{"domain":"www.paypal.com","hostOnly":true,"httpOnly":true,"name":"nsid","path":"/","sameSite":"no_restriction","secure":true,"session":true,"storeId":"0","value":"s%3AN9UJZo4tcTvaEo64NdYa3GnLJ-Es4g1r.TKNku%2Bk%2BBUC0r%2BYW0xl9IPRGP91zdPsezeFraaRJcNM"},{"domain":".paypal.com","expirationDate":1765806992.746587,"hostOnly":false,"httpOnly":false,"name":"ts_c","path":"/","sameSite":"no_restriction","secure":true,"session":false,"storeId":"0","value":"vr%3D7d217bfb1930aa3008fbbe92f8e75dde%26vt%3Dca9af7751930a551b0753a2bf4bd44de"},{"domain":".paypal.com","expirationDate":1734272792.74547,"hostOnly":false,"httpOnly":true,"name":"l7_az","path":"/","sameSite":"no_restriction","secure":true,"session":false,"storeId":"0","value":"dcg16.slc"},{"domain":".paypal.com","expirationDate":1734271036,"hostOnly":false,"httpOnly":false,"name":"_gat_gtag_UA_53389718_12","path":"/","sameSite":"unspecified","secure":false,"session":false,"storeId":"0","value":"1"},{"domain":"www.paypal.com","expirationDate":1734272777.25904,"hostOnly":true,"httpOnly":true,"name":"lpv925803","path":"/","sameSite":"no_restriction","secure":true,"session":false,"storeId":"0","value":"aHR0cHM6Ly93d3cucGF5cGFsLmNvbS9hdS9ob21l"},{"domain":".paypal.com","hostOnly":false,"httpOnly":false,"name":"TLTSID","path":"/","sameSite":"strict","secure":true,"session":true,"storeId":"0","value":"72443986758784130385591175069841"},{"domain":".paypal.com","expirationDate":1734271877.877047,"hostOnly":false,"httpOnly":false,"name":"rssk","path":"/","sameSite":"no_restriction","secure":true,"session":false,"storeId":"0","value":"d%7DC9%40977%3C4%3A%40%3D%40%40%3C%3Exqx%3Ek%7D%3C%7Fr%7C%3B%3E%3F14"},{"domain":".paypal.com","hostOnly":false,"httpOnly":true,"name":"id_token","path":"/","sameSite":"no_restriction","secure":true,"session":true,"storeId":"0","value":"idtoken9a381e52bd744251ac974a7321f32358"},{"domain":".paypal.com","hostOnly":false,"httpOnly":true,"name":"AV894Kt2TSumQQrJwe-8mzmyREO","path":"/","sameSite":"no_restriction","secure":true,"session":true,"storeId":"0","value":"S23AANXeNosttVvpPZ7JCIWlMIM05nOo2lMxhLMoxwZkup8XS6pQD5fpPvaYhe_SoYZTobAX0iGMdUSme4pAGzpuZy4rmjqHQ"},{"domain":".paypal.com","expirationDate":1768830986.949214,"hostOnly":false,"httpOnly":true,"name":"KHcl0EuY7AKSMgfvHl7J5E7hPtK","path":"/","sameSite":"no_restriction","secure":true,"session":false,"storeId":"0","value":"h4so4a9Vdy4fUY9oHO9xcn9sv-gyx-DYfpOASxGLO8qJHG4ZeAepldPA2R_Gs6S_ZiR9Y4YZcqycBPZE"},{"domain":".paypal.com","hostOnly":false,"httpOnly":true,"name":"HaC80bwXscjqZ7KM6VOxULOB534","path":"/","sameSite":"no_restriction","secure":true,"session":true,"storeId":"0","value":"_G7BJ4oHs7FNonRXimSFUqxpn-r7Hh-hRXAgk2eHPJcKpOkG0mQRAkjyBe6f1aUQt4_hWuwS-euDlCi2XC8AbdNxRjhBXeOh-867rRns2KXcYGfoqXTtmhGj20pQGP83i_CfNm"},{"domain":".paypal.com","expirationDate":1736862987.834698,"hostOnly":false,"httpOnly":false,"name":"datadome","path":"/","sameSite":"lax","secure":true,"session":false,"storeId":"0","value":"oM5cmqh4C3AU_gPAdN4tmaY3lbWduASpsWlwEXdNLAv9B1uO2cbvEzzp9bfaW8XjfNcCNrlJez840v9PrZHvgh0Srz~ttCUzjFznGezHmtAbtarT7cjlrv9l8KZRQ5vs"},{"domain":".paypal.com","expirationDate":1768830989.458216,"hostOnly":false,"httpOnly":false,"name":"_ga","path":"/","sameSite":"unspecified","secure":false,"session":false,"storeId":"0","value":"GA1.2.1812577430.1733812621"},{"domain":".paypal.com","hostOnly":false,"httpOnly":true,"name":"SEGM","path":"/","sameSite":"unspecified","secure":true,"session":true,"storeId":"0","value":"bRdV1vB0ebq9RKdAb3xSHowCi6QnnlCiDOLNk8i1mAuLl1vTbzHQwWajSsMe8mvoWiJtY1GnpzN4Y-sixGy7BQ"},{"domain":".paypal.com","expirationDate":1768830990.470592,"hostOnly":false,"httpOnly":false,"name":"_ga_FQYH6BLY4K","path":"/","sameSite":"unspecified","secure":false,"session":false,"storeId":"0","value":"GS1.1.1734270974.4.1.1734270990.0.0.0"},{"domain":".paypal.com","hostOnly":false,"httpOnly":true,"name":"x-pp-s","path":"/","sameSite":"no_restriction","secure":true,"session":true,"storeId":"0","value":"eyJ0IjoiMTczNDI3MDk5MjM1NSIsImwiOiIwIiwibSI6IjAifQ"},{"domain":".paypal.com","expirationDate":1734530192.475875,"hostOnly":false,"httpOnly":true,"name":"tsrce","path":"/","sameSite":"no_restriction","secure":true,"session":false,"storeId":"0","value":"privacynodeweb"},{"domain":".paypal.com","expirationDate":1765806992.746484,"hostOnly":false,"httpOnly":true,"name":"ts","path":"/","sameSite":"no_restriction","secure":true,"session":false,"storeId":"0","value":"vreXpYrS%3D1765806992%26vteXpYrS%3D1734272792%26vr%3D7d217bfb1930aa3008fbbe92f8e75dde%26vt%3Dca9af7751930a551b0753a2bf4bd44de%26vtyp%3Dreturn"},{"domain":"www.paypal.com","expirationDate":1734271895,"hostOnly":true,"httpOnly":false,"name":"_dd_s","path":"/","sameSite":"strict","secure":false,"session":false,"storeId":"0","value":"rum=2&id=feadf20d-cc7c-4014-92d3-6af68994c66c&created=1734270974362&expire=1734271894414"}]